CHANGES.txt
README.txt
setup.py
src/Products/__init__.py
src/Products.IntelliDateTime.egg-info/PKG-INFO
src/Products.IntelliDateTime.egg-info/SOURCES.txt
src/Products.IntelliDateTime.egg-info/dependency_links.txt
src/Products.IntelliDateTime.egg-info/entry_points.txt
src/Products.IntelliDateTime.egg-info/namespace_packages.txt
src/Products.IntelliDateTime.egg-info/not-zip-safe
src/Products.IntelliDateTime.egg-info/requires.txt
src/Products.IntelliDateTime.egg-info/top_level.txt
src/Products/IntelliDateTime/__init__.py
src/Products/IntelliDateTime/config.py
src/Products/IntelliDateTime/configure.zcml
src/Products/IntelliDateTime/field.py
src/Products/IntelliDateTime/interfaces.py
src/Products/IntelliDateTime/version.txt
src/Products/IntelliDateTime/widget.py
src/Products/IntelliDateTime/Extensions/Install.py
src/Products/IntelliDateTime/Extensions/__init__.py
src/Products/IntelliDateTime/skins/intellidatetime/intellidatetime.js
src/Products/IntelliDateTime/skins/intellidatetime/intellidatetime.pt
src/Products/IntelliDateTime/skins/intellidatetime/intellidatetime_macros.pt