Metadata-Version: 1.0
Name: Products.IntelliDateTime
Version: 1.3.1
Summary: Archetypes Datetime Widget using bda.intellidatetime conversion
Home-page: https://svn.plone.org/svn/archetypes/MoreFieldsAndWidgets/IntelliDateTime
Author: Robert Niederreiter
Author-email: rnix@squarewave.at
License: General Public Licence
Platform: UNKNOWN
Classifier: Development Status :: 5 - Production/Stable
Classifier: Environment :: Web Environment
Classifier: Framework :: Zope2
Classifier: License :: OSI Approved :: GNU General Public License (GPL)
Classifier: Operating System :: OS Independent
Classifier: Programming Language :: Python
Classifier: Topic :: Internet :: WWW/HTTP :: Dynamic Content
